plover_platform_specific_translation/__init__.py
plover_platform_specific_translation/extension.py
plover_platform_specific_translation/config/__init__.py
plover_platform_specific_translation/config/file.py
plover_platform_specific_translation/config/loader.py
plover_platform_specific_translation/config/transformer.py
plover_platform_specific_translation/platform/__init__.py
plover_platform_specific_translation/platform/parser.py
plover_platform_specific_translation/translation/__init__.py
plover_platform_specific_translation/translation/resolver.py
plover_platform_specific_translation-0.3.0.dist-info/LICENSE.txt
plover_platform_specific_translation-0.3.0.dist-info/METADATA
plover_platform_specific_translation-0.3.0.dist-info/WHEEL
plover_platform_specific_translation-0.3.0.dist-info/entry_points.txt
plover_platform_specific_translation-0.3.0.dist-info/top_level.txt
plover_platform_specific_translation-0.3.0.dist-info/zip-safe
plover_platform_specific_translation-0.3.0.dist-info/RECORD
